{
  "name": "Central 190",
  "version": "2.4.0",
  "phase": 30,
  "build": "CENTRAL190-2400-F30-RC-PUBLICA-COMERCIAL-20260622-123500-BRT",
  "compiledAt": "2026-06-22T12:35:00-03:00",
  "saveSchema": 28,
  "title": "RC pública/comercial, tutorial, performance e publicação",
  "preserved": [
    "mobile homologation",
    "animated units",
    "typewriter",
    "field radio",
    "resource dispatch",
    "progressive map",
    "campaign",
    "career",
    "training",
    "visual curation",
    "realistic multi-step cases",
    "final balance"
  ],
  "added": [
    "C190_Tutorial module v1",
    "C190_PublicRC checklist v1",
    "guided first shift",
    "public release checklist",
    "PWA cache v2.4.0",
    "settings duplicate input fix"
  ]
}