{
  "name": "Central 190",
  "version": "3.2.0",
  "phase": 38,
  "build": "CENTRAL190-3200-F38-DEBRIEFING-PROFISSIONAL-20260624-112500-BRT",
  "compiledAt": "2026-06-24T11:25:00-03:00",
  "saveSchema": 35,
  "title": "Debriefing profissional, replay de decisão e plano de melhoria",
  "preserved": [
    "supervisor operacional F37",
    "central multitarefa F36",
    "fluxo pós-despacho",
    "mapa cinematográfico e ETA visual",
    "áudio e voz PT-BR",
    "Defesa Civil e Águia",
    "veículos PNG SP",
    "tutorial visível",
    "campanha, carreira e cursos"
  ],
  "added": [
    "novo módulo js/debriefing.js",
    "painel Debriefing Profissional em Relatórios",
    "replay de decisões por ocorrência",
    "plano de melhoria por fraqueza operacional",
    "treino recomendado após plantão",
    "tendência de evolução do operador"
  ]
}